r2ntab/__init__.py
r2ntab/drnet.py
r2ntab/r2ntab.py
r2ntab/sparse_linear.py
r2ntab-1.0.2.dist-info/LICENSE
r2ntab-1.0.2.dist-info/METADATA
r2ntab-1.0.2.dist-info/WHEEL
r2ntab-1.0.2.dist-info/top_level.txt
r2ntab-1.0.2.dist-info/RECORD
