Metadata-Version: 2.1
Name: r2ntab
Version: 1.0.2
Summary: Interpretable machine learning model for binary classification combining deep learning and rule learning
Author: M.J. van der Zwart
Author-email: mvdzwart01@hotmail.nl
Keywords: python,rule learning,neural networks,deep learning,classification
Classifier: Programming Language :: Python :: 3.8
Classifier: License :: OSI Approved :: MIT License
Classifier: Operating System :: OS Independent
Requires-Python: >=3.8
License-File: LICENSE
Requires-Dist: torch
Requires-Dist: torchvision
Requires-Dist: numpy
Requires-Dist: tqdm
Requires-Dist: pandas
Requires-Dist: scikit-learn
Requires-Dist: scipy
